{
  "car": [
    {
      "category": "Convertibles", 
      "url": "/mini/cooper-convertible/2013-mini-cooper-convertible/convertible-2d/options/?vehicleid=383074&intent=buy-used&category=convertible", 
      "make": "MINI", 
      "sub_cat": "Convertible 2D", 
      "year": "2013", 
      "model": "Cooper Convertible", 
      "car_id": "383074"
    }, 
    {
      "category": "Convertibles", 
      "url": "/mini/cooper-convertible/2013-mini-cooper-convertible/s-convertible-2d/options/?vehicleid=383076&intent=buy-used&category=convertible", 
      "make": "MINI", 
      "sub_cat": "S Convertible 2D", 
      "year": "2013", 
      "model": "Cooper Convertible", 
      "car_id": "383076"
    }, 
    {
      "category": "Convertibles", 
      "url": "/mini/cooper-convertible/2013-mini-cooper-convertible/john-cooper-works-convertible-2d/options/?vehicleid=383081&intent=buy-used&category=convertible", 
      "make": "MINI", 
      "sub_cat": "John Cooper Works Convertible 2D", 
      "year": "2013", 
      "model": "Cooper Convertible", 
      "car_id": "383081"
    }, 
    {
      "category": "Convertibles", 
      "url": "/mini/cooper-convertible/2012-mini-cooper-convertible/convertible-2d/options/?vehicleid=382887&intent=buy-used&category=convertible", 
      "make": "MINI", 
      "sub_cat": "Convertible 2D", 
      "year": "2012", 
      "model": "Cooper Convertible", 
      "car_id": "382887"
    }, 
    {
      "category": "Convertibles", 
      "url": "/mini/cooper-convertible/2012-mini-cooper-convertible/s-convertible-2d/options/?vehicleid=382888&intent=buy-used&category=convertible", 
      "make": "MINI", 
      "sub_cat": "S Convertible 2D", 
      "year": "2012", 
      "model": "Cooper Convertible", 
      "car_id": "382888"
    }, 
    {
      "category": "Convertibles", 
      "url": "/mini/cooper-convertible/2012-mini-cooper-convertible/john-cooper-works-convertible-2d/options/?vehicleid=382889&intent=buy-used&category=convertible", 
      "make": "MINI", 
      "sub_cat": "John Cooper Works Convertible 2D", 
      "year": "2012", 
      "model": "Cooper Convertible", 
      "car_id": "382889"
    }, 
    {
      "category": "Convertibles", 
      "url": "/mini/cooper-convertible/2011-mini-cooper-convertible/convertible-2d/options/?vehicleid=382848&intent=buy-used&category=convertible", 
      "make": "MINI", 
      "sub_cat": "Convertible 2D", 
      "year": "2011", 
      "model": "Cooper Convertible", 
      "car_id": "382848"
    }, 
    {
      "category": "Convertibles", 
      "url": "/mini/cooper-convertible/2011-mini-cooper-convertible/s-convertible-2d/options/?vehicleid=382850&intent=buy-used&category=convertible", 
      "make": "MINI", 
      "sub_cat": "S Convertible 2D", 
      "year": "2011", 
      "model": "Cooper Convertible", 
      "car_id": "382850"
    }, 
    {
      "category": "Convertibles", 
      "url": "/mini/cooper-convertible/2011-mini-cooper-convertible/john-cooper-works-convertible-2d/options/?vehicleid=382849&intent=buy-used&category=convertible", 
      "make": "MINI", 
      "sub_cat": "John Cooper Works Convertible 2D", 
      "year": "2011", 
      "model": "Cooper Convertible", 
      "car_id": "382849"
    }, 
    {
      "category": "Convertibles", 
      "url": "/mini/cooper-convertible/2010-mini-cooper-convertible/convertible-2d/options/?vehicleid=382852&intent=buy-used&category=convertible", 
      "make": "MINI", 
      "sub_cat": "Convertible 2D", 
      "year": "2010", 
      "model": "Cooper Convertible", 
      "car_id": "382852"
    }, 
    {
      "category": "Convertibles", 
      "url": "/mini/cooper-convertible/2010-mini-cooper-convertible/s-convertible-2d/options/?vehicleid=382853&intent=buy-used&category=convertible", 
      "make": "MINI", 
      "sub_cat": "S Convertible 2D", 
      "year": "2010", 
      "model": "Cooper Convertible", 
      "car_id": "382853"
    }, 
    {
      "category": "Convertibles", 
      "url": "/mini/cooper-convertible/2010-mini-cooper-convertible/john-cooper-works-convertible-2d/options/?vehicleid=382863&intent=buy-used&category=convertible", 
      "make": "MINI", 
      "sub_cat": "John Cooper Works Convertible 2D", 
      "year": "2010", 
      "model": "Cooper Convertible", 
      "car_id": "382863"
    }, 
    {
      "category": "Convertibles", 
      "url": "/mini/cooper-convertible/2009-mini-cooper-convertible/convertible-2d/options/?vehicleid=382856&intent=buy-used&category=convertible", 
      "make": "MINI", 
      "sub_cat": "Convertible 2D", 
      "year": "2009", 
      "model": "Cooper Convertible", 
      "car_id": "382856"
    }, 
    {
      "category": "Convertibles", 
      "url": "/mini/cooper-convertible/2009-mini-cooper-convertible/s-convertible-2d/options/?vehicleid=382859&intent=buy-used&category=convertible", 
      "make": "MINI", 
      "sub_cat": "S Convertible 2D", 
      "year": "2009", 
      "model": "Cooper Convertible", 
      "car_id": "382859"
    }, 
    {
      "category": "Convertibles", 
      "url": "/mini/cooper-convertible/2009-mini-cooper-convertible/john-cooper-works-convertible-2d/options/?vehicleid=382860&intent=buy-used&category=convertible", 
      "make": "MINI", 
      "sub_cat": "John Cooper Works Convertible 2D", 
      "year": "2009", 
      "model": "Cooper Convertible", 
      "car_id": "382860"
    }, 
    {
      "category": "Convertibles", 
      "url": "/mini/cooper-convertible/2008-mini-cooper-convertible/convertible-2d/options/?vehicleid=382874&intent=buy-used&category=convertible", 
      "make": "MINI", 
      "sub_cat": "Convertible 2D", 
      "year": "2008", 
      "model": "Cooper Convertible", 
      "car_id": "382874"
    }, 
    {
      "category": "Convertibles", 
      "url": "/mini/cooper-convertible/2008-mini-cooper-convertible/s-convertible-2d/options/?vehicleid=382865&intent=buy-used&category=convertible", 
      "make": "MINI", 
      "sub_cat": "S Convertible 2D", 
      "year": "2008", 
      "model": "Cooper Convertible", 
      "car_id": "382865"
    }, 
    {
      "category": "Convertibles", 
      "url": "/mini/cooper-convertible/2007-mini-cooper-convertible/convertible-2d/options/?vehicleid=382866&intent=buy-used&category=convertible", 
      "make": "MINI", 
      "sub_cat": "Convertible 2D", 
      "year": "2007", 
      "model": "Cooper Convertible", 
      "car_id": "382866"
    }, 
    {
      "category": "Convertibles", 
      "url": "/mini/cooper-convertible/2007-mini-cooper-convertible/s-convertible-2d/options/?vehicleid=382878&intent=buy-used&category=convertible", 
      "make": "MINI", 
      "sub_cat": "S Convertible 2D", 
      "year": "2007", 
      "model": "Cooper Convertible", 
      "car_id": "382878"
    }, 
    {
      "category": "Convertibles", 
      "url": "/mini/cooper-convertible/2006-mini-cooper-convertible/convertible-2d/options/?vehicleid=382871&intent=buy-used&category=convertible", 
      "make": "MINI", 
      "sub_cat": "Convertible 2D", 
      "year": "2006", 
      "model": "Cooper Convertible", 
      "car_id": "382871"
    }, 
    {
      "category": "Convertibles", 
      "url": "/mini/cooper-convertible/2006-mini-cooper-convertible/s-convertible-2d/options/?vehicleid=382872&intent=buy-used&category=convertible", 
      "make": "MINI", 
      "sub_cat": "S Convertible 2D", 
      "year": "2006", 
      "model": "Cooper Convertible", 
      "car_id": "382872"
    }, 
    {
      "category": "Convertibles", 
      "url": "/mini/cooper-convertible/2005-mini-cooper-convertible/convertible-2d/options/?vehicleid=382861&intent=buy-used&category=convertible", 
      "make": "MINI", 
      "sub_cat": "Convertible 2D", 
      "year": "2005", 
      "model": "Cooper Convertible", 
      "car_id": "382861"
    }, 
    {
      "category": "Convertibles", 
      "url": "/mini/cooper-convertible/2005-mini-cooper-convertible/s-convertible-2d/options/?vehicleid=382862&intent=buy-used&category=convertible", 
      "make": "MINI", 
      "sub_cat": "S Convertible 2D", 
      "year": "2005", 
      "model": "Cooper Convertible", 
      "car_id": "382862"
    }, 
    {
      "category": "Convertibles", 
      "url": "/mini/cooper-roadster/2013-mini-cooper-roadster/roadster-2d/options/?vehicleid=383069&intent=buy-used&category=convertible", 
      "make": "MINI", 
      "sub_cat": "Roadster 2D", 
      "year": "2013", 
      "model": "Cooper Roadster", 
      "car_id": "383069"
    }, 
    {
      "category": "Convertibles", 
      "url": "/mini/cooper-roadster/2013-mini-cooper-roadster/s-roadster-2d/options/?vehicleid=383066&intent=buy-used&category=convertible", 
      "make": "MINI", 
      "sub_cat": "S Roadster 2D", 
      "year": "2013", 
      "model": "Cooper Roadster", 
      "car_id": "383066"
    }, 
    {
      "category": "Convertibles", 
      "url": "/mini/cooper-roadster/2013-mini-cooper-roadster/john-cooper-works-roadster-2d/options/?vehicleid=383068&intent=buy-used&category=convertible", 
      "make": "MINI", 
      "sub_cat": "John Cooper Works Roadster 2D", 
      "year": "2013", 
      "model": "Cooper Roadster", 
      "car_id": "383068"
    }, 
    {
      "category": "Convertibles", 
      "url": "/mini/cooper-roadster/2012-mini-cooper-roadster/roadster-2d/options/?vehicleid=374109&intent=buy-used&category=convertible", 
      "make": "MINI", 
      "sub_cat": "Roadster 2D", 
      "year": "2012", 
      "model": "Cooper Roadster", 
      "car_id": "374109"
    }, 
    {
      "category": "Convertibles", 
      "url": "/mini/cooper-roadster/2012-mini-cooper-roadster/s-roadster-2d/options/?vehicleid=374116&intent=buy-used&category=convertible", 
      "make": "MINI", 
      "sub_cat": "S Roadster 2D", 
      "year": "2012", 
      "model": "Cooper Roadster", 
      "car_id": "374116"
    }, 
    {
      "category": "Convertibles", 
      "url": "/mini/cooper-roadster/2012-mini-cooper-roadster/john-cooper-works-roadster-2d/options/?vehicleid=374112&intent=buy-used&category=convertible", 
      "make": "MINI", 
      "sub_cat": "John Cooper Works Roadster 2D", 
      "year": "2012", 
      "model": "Cooper Roadster", 
      "car_id": "374112"
    }, 
    {
      "category": "Coupes", 
      "url": "/mini/cooper/2008-mini-cooper/hatchback-2d/options/?vehicleid=197433&intent=buy-used&category=coupe", 
      "make": "MINI", 
      "sub_cat": "Hatchback 2D", 
      "year": "2008", 
      "model": "Cooper", 
      "car_id": "197433"
    }, 
    {
      "category": "Coupes", 
      "url": "/mini/cooper/2008-mini-cooper/s-hatchback-2d/options/?vehicleid=197429&intent=buy-used&category=coupe", 
      "make": "MINI", 
      "sub_cat": "S Hatchback 2D", 
      "year": "2008", 
      "model": "Cooper", 
      "car_id": "197429"
    }, 
    {
      "category": "Coupes", 
      "url": "/mini/cooper/2007-mini-cooper/hatchback-2d/options/?vehicleid=83995&intent=buy-used&category=coupe", 
      "make": "MINI", 
      "sub_cat": "Hatchback 2D", 
      "year": "2007", 
      "model": "Cooper", 
      "car_id": "83995"
    }, 
    {
      "category": "Coupes", 
      "url": "/mini/cooper/2007-mini-cooper/s-hatchback-2d/options/?vehicleid=83993&intent=buy-used&category=coupe", 
      "make": "MINI", 
      "sub_cat": "S Hatchback 2D", 
      "year": "2007", 
      "model": "Cooper", 
      "car_id": "83993"
    }, 
    {
      "category": "Coupes", 
      "url": "/mini/cooper/2006-mini-cooper/hatchback-2d/options/?vehicleid=994&intent=buy-used&category=coupe", 
      "make": "MINI", 
      "sub_cat": "Hatchback 2D", 
      "year": "2006", 
      "model": "Cooper", 
      "car_id": "994"
    }, 
    {
      "category": "Coupes", 
      "url": "/mini/cooper/2006-mini-cooper/s-hatchback-2d/options/?vehicleid=997&intent=buy-used&category=coupe", 
      "make": "MINI", 
      "sub_cat": "S Hatchback 2D", 
      "year": "2006", 
      "model": "Cooper", 
      "car_id": "997"
    }, 
    {
      "category": "Coupes", 
      "url": "/mini/cooper/2006-mini-cooper/s-gp-hatchback-2d/options/?vehicleid=43512&intent=buy-used&category=coupe", 
      "make": "MINI", 
      "sub_cat": "S GP Hatchback 2D", 
      "year": "2006", 
      "model": "Cooper", 
      "car_id": "43512"
    }, 
    {
      "category": "Coupes", 
      "url": "/mini/cooper/2005-mini-cooper/hatchback-2d/options/?vehicleid=1119&intent=buy-used&category=coupe", 
      "make": "MINI", 
      "sub_cat": "Hatchback 2D", 
      "year": "2005", 
      "model": "Cooper", 
      "car_id": "1119"
    }, 
    {
      "category": "Coupes", 
      "url": "/mini/cooper/2005-mini-cooper/s-hatchback-2d/options/?vehicleid=1116&intent=buy-used&category=coupe", 
      "make": "MINI", 
      "sub_cat": "S Hatchback 2D", 
      "year": "2005", 
      "model": "Cooper", 
      "car_id": "1116"
    }, 
    {
      "category": "Coupes", 
      "url": "/mini/cooper/2004-mini-cooper/hatchback-2d/options/?vehicleid=2929&intent=buy-used&category=coupe", 
      "make": "MINI", 
      "sub_cat": "Hatchback 2D", 
      "year": "2004", 
      "model": "Cooper", 
      "car_id": "2929"
    }, 
    {
      "category": "Coupes", 
      "url": "/mini/cooper/2004-mini-cooper/s-hatchback-2d/options/?vehicleid=2937&intent=buy-used&category=coupe", 
      "make": "MINI", 
      "sub_cat": "S Hatchback 2D", 
      "year": "2004", 
      "model": "Cooper", 
      "car_id": "2937"
    }, 
    {
      "category": "Coupes", 
      "url": "/mini/cooper/2003-mini-cooper/hatchback-2d/options/?vehicleid=2689&intent=buy-used&category=coupe", 
      "make": "MINI", 
      "sub_cat": "Hatchback 2D", 
      "year": "2003", 
      "model": "Cooper", 
      "car_id": "2689"
    }, 
    {
      "category": "Coupes", 
      "url": "/mini/cooper/2003-mini-cooper/s-hatchback-2d/options/?vehicleid=2693&intent=buy-used&category=coupe", 
      "make": "MINI", 
      "sub_cat": "S Hatchback 2D", 
      "year": "2003", 
      "model": "Cooper", 
      "car_id": "2693"
    }, 
    {
      "category": "Coupes", 
      "url": "/mini/cooper/2002-mini-cooper/hatchback-2d/options/?vehicleid=4340&intent=buy-used&category=coupe", 
      "make": "MINI", 
      "sub_cat": "Hatchback 2D", 
      "year": "2002", 
      "model": "Cooper", 
      "car_id": "4340"
    }, 
    {
      "category": "Coupes", 
      "url": "/mini/cooper/2002-mini-cooper/s-hatchback-2d/options/?vehicleid=4345&intent=buy-used&category=coupe", 
      "make": "MINI", 
      "sub_cat": "S Hatchback 2D", 
      "year": "2002", 
      "model": "Cooper", 
      "car_id": "4345"
    }, 
    {
      "category": "Coupes", 
      "url": "/mini/cooper-clubman/2014-mini-cooper-clubman/hatchback-2d/options/?vehicleid=393429&intent=buy-used&category=coupe", 
      "make": "MINI", 
      "sub_cat": "Hatchback 2D", 
      "year": "2014", 
      "model": "Cooper Clubman", 
      "car_id": "393429"
    }, 
    {
      "category": "Coupes", 
      "url": "/mini/cooper-clubman/2014-mini-cooper-clubman/s-hatchback-2d/options/?vehicleid=393438&intent=buy-used&category=coupe", 
      "make": "MINI", 
      "sub_cat": "S Hatchback 2D", 
      "year": "2014", 
      "model": "Cooper Clubman", 
      "car_id": "393438"
    }, 
    {
      "category": "Coupes", 
      "url": "/mini/cooper-clubman/2013-mini-cooper-clubman/hatchback-2d/options/?vehicleid=383064&intent=buy-used&category=coupe", 
      "make": "MINI", 
      "sub_cat": "Hatchback 2D", 
      "year": "2013", 
      "model": "Cooper Clubman", 
      "car_id": "383064"
    }, 
    {
      "category": "Coupes", 
      "url": "/mini/cooper-clubman/2013-mini-cooper-clubman/s-hatchback-2d/options/?vehicleid=383063&intent=buy-used&category=coupe", 
      "make": "MINI", 
      "sub_cat": "S Hatchback 2D", 
      "year": "2013", 
      "model": "Cooper Clubman", 
      "car_id": "383063"
    }, 
    {
      "category": "Coupes", 
      "url": "/mini/cooper-clubman/2013-mini-cooper-clubman/john-cooper-works-hatchback-2d/options/?vehicleid=383065&intent=buy-used&category=coupe", 
      "make": "MINI", 
      "sub_cat": "John Cooper Works Hatchback 2D", 
      "year": "2013", 
      "model": "Cooper Clubman", 
      "car_id": "383065"
    }, 
    {
      "category": "Coupes", 
      "url": "/mini/cooper-clubman/2012-mini-cooper-clubman/hatchback-2d/options/?vehicleid=373334&intent=buy-used&category=coupe", 
      "make": "MINI", 
      "sub_cat": "Hatchback 2D", 
      "year": "2012", 
      "model": "Cooper Clubman", 
      "car_id": "373334"
    }, 
    {
      "category": "Coupes", 
      "url": "/mini/cooper-clubman/2012-mini-cooper-clubman/s-hatchback-2d/options/?vehicleid=373330&intent=buy-used&category=coupe", 
      "make": "MINI", 
      "sub_cat": "S Hatchback 2D", 
      "year": "2012", 
      "model": "Cooper Clubman", 
      "car_id": "373330"
    }, 
    {
      "category": "Coupes", 
      "url": "/mini/cooper-clubman/2012-mini-cooper-clubman/john-cooper-works-hatchback-2d/options/?vehicleid=373329&intent=buy-used&category=coupe", 
      "make": "MINI", 
      "sub_cat": "John Cooper Works Hatchback 2D", 
      "year": "2012", 
      "model": "Cooper Clubman", 
      "car_id": "373329"
    }, 
    {
      "category": "Coupes", 
      "url": "/mini/cooper-clubman/2011-mini-cooper-clubman/hatchback-2d/options/?vehicleid=358422&intent=buy-used&category=coupe", 
      "make": "MINI", 
      "sub_cat": "Hatchback 2D", 
      "year": "2011", 
      "model": "Cooper Clubman", 
      "car_id": "358422"
    }, 
    {
      "category": "Coupes", 
      "url": "/mini/cooper-clubman/2011-mini-cooper-clubman/s-hatchback-2d/options/?vehicleid=358420&intent=buy-used&category=coupe", 
      "make": "MINI", 
      "sub_cat": "S Hatchback 2D", 
      "year": "2011", 
      "model": "Cooper Clubman", 
      "car_id": "358420"
    }, 
    {
      "category": "Coupes", 
      "url": "/mini/cooper-clubman/2011-mini-cooper-clubman/john-cooper-works-hatchback-2d/options/?vehicleid=358421&intent=buy-used&category=coupe", 
      "make": "MINI", 
      "sub_cat": "John Cooper Works Hatchback 2D", 
      "year": "2011", 
      "model": "Cooper Clubman", 
      "car_id": "358421"
    }, 
    {
      "category": "Coupes", 
      "url": "/mini/cooper-clubman/2010-mini-cooper-clubman/hatchback-2d/options/?vehicleid=358338&intent=buy-used&category=coupe", 
      "make": "MINI", 
      "sub_cat": "Hatchback 2D", 
      "year": "2010", 
      "model": "Cooper Clubman", 
      "car_id": "358338"
    }, 
    {
      "category": "Coupes", 
      "url": "/mini/cooper-clubman/2010-mini-cooper-clubman/s-hatchback-2d/options/?vehicleid=358322&intent=buy-used&category=coupe", 
      "make": "MINI", 
      "sub_cat": "S Hatchback 2D", 
      "year": "2010", 
      "model": "Cooper Clubman", 
      "car_id": "358322"
    }, 
    {
      "category": "Coupes", 
      "url": "/mini/cooper-clubman/2010-mini-cooper-clubman/john-cooper-works-hatchback-2d/options/?vehicleid=358321&intent=buy-used&category=coupe", 
      "make": "MINI", 
      "sub_cat": "John Cooper Works Hatchback 2D", 
      "year": "2010", 
      "model": "Cooper Clubman", 
      "car_id": "358321"
    }, 
    {
      "category": "Coupes", 
      "url": "/mini/cooper-clubman/2009-mini-cooper-clubman/hatchback-2d/options/?vehicleid=358351&intent=buy-used&category=coupe", 
      "make": "MINI", 
      "sub_cat": "Hatchback 2D", 
      "year": "2009", 
      "model": "Cooper Clubman", 
      "car_id": "358351"
    }, 
    {
      "category": "Coupes", 
      "url": "/mini/cooper-clubman/2009-mini-cooper-clubman/s-hatchback-2d/options/?vehicleid=358336&intent=buy-used&category=coupe", 
      "make": "MINI", 
      "sub_cat": "S Hatchback 2D", 
      "year": "2009", 
      "model": "Cooper Clubman", 
      "car_id": "358336"
    }, 
    {
      "category": "Coupes", 
      "url": "/mini/cooper-clubman/2009-mini-cooper-clubman/john-cooper-works-hatchback-2d/options/?vehicleid=358335&intent=buy-used&category=coupe", 
      "make": "MINI", 
      "sub_cat": "John Cooper Works Hatchback 2D", 
      "year": "2009", 
      "model": "Cooper Clubman", 
      "car_id": "358335"
    }, 
    {
      "category": "Coupes", 
      "url": "/mini/cooper-clubman/2008-mini-cooper-clubman/hatchback-2d/options/?vehicleid=358349&intent=buy-used&category=coupe", 
      "make": "MINI", 
      "sub_cat": "Hatchback 2D", 
      "year": "2008", 
      "model": "Cooper Clubman", 
      "car_id": "358349"
    }, 
    {
      "category": "Coupes", 
      "url": "/mini/cooper-clubman/2008-mini-cooper-clubman/s-hatchback-2d/options/?vehicleid=358350&intent=buy-used&category=coupe", 
      "make": "MINI", 
      "sub_cat": "S Hatchback 2D", 
      "year": "2008", 
      "model": "Cooper Clubman", 
      "car_id": "358350"
    }, 
    {
      "category": "Coupes", 
      "url": "/mini/cooper-coupe/2013-mini-cooper-coupe/coupe-2d/options/?vehicleid=383067&intent=buy-used&category=coupe", 
      "make": "MINI", 
      "sub_cat": "Coupe 2D", 
      "year": "2013", 
      "model": "Cooper Coupe", 
      "car_id": "383067"
    }, 
    {
      "category": "Coupes", 
      "url": "/mini/cooper-coupe/2013-mini-cooper-coupe/s-coupe-2d/options/?vehicleid=383070&intent=buy-used&category=coupe", 
      "make": "MINI", 
      "sub_cat": "S Coupe 2D", 
      "year": "2013", 
      "model": "Cooper Coupe", 
      "car_id": "383070"
    }, 
    {
      "category": "Coupes", 
      "url": "/mini/cooper-coupe/2013-mini-cooper-coupe/john-cooper-works-coupe-2d/options/?vehicleid=383071&intent=buy-used&category=coupe", 
      "make": "MINI", 
      "sub_cat": "John Cooper Works Coupe 2D", 
      "year": "2013", 
      "model": "Cooper Coupe", 
      "car_id": "383071"
    }, 
    {
      "category": "Coupes", 
      "url": "/mini/cooper-coupe/2012-mini-cooper-coupe/coupe-2d/options/?vehicleid=372339&intent=buy-used&category=coupe", 
      "make": "MINI", 
      "sub_cat": "Coupe 2D", 
      "year": "2012", 
      "model": "Cooper Coupe", 
      "car_id": "372339"
    }, 
    {
      "category": "Coupes", 
      "url": "/mini/cooper-coupe/2012-mini-cooper-coupe/s-coupe-2d/options/?vehicleid=372324&intent=buy-used&category=coupe", 
      "make": "MINI", 
      "sub_cat": "S Coupe 2D", 
      "year": "2012", 
      "model": "Cooper Coupe", 
      "car_id": "372324"
    }, 
    {
      "category": "Coupes", 
      "url": "/mini/cooper-coupe/2012-mini-cooper-coupe/john-cooper-works-coupe-2d/options/?vehicleid=372325&intent=buy-used&category=coupe", 
      "make": "MINI", 
      "sub_cat": "John Cooper Works Coupe 2D", 
      "year": "2012", 
      "model": "Cooper Coupe", 
      "car_id": "372325"
    }, 
    {
      "category": "Coupes", 
      "url": "/mini/cooper-hardtop/2013-mini-cooper-hardtop/hatchback-2d/options/?vehicleid=383075&intent=buy-used&category=coupe", 
      "make": "MINI", 
      "sub_cat": "Hatchback 2D", 
      "year": "2013", 
      "model": "Cooper Hardtop", 
      "car_id": "383075"
    }, 
    {
      "category": "Coupes", 
      "url": "/mini/cooper-hardtop/2013-mini-cooper-hardtop/s-hatchback-2d/options/?vehicleid=383072&intent=buy-used&category=coupe", 
      "make": "MINI", 
      "sub_cat": "S Hatchback 2D", 
      "year": "2013", 
      "model": "Cooper Hardtop", 
      "car_id": "383072"
    }, 
    {
      "category": "Coupes", 
      "url": "/mini/cooper-hardtop/2013-mini-cooper-hardtop/john-cooper-works-hatchback-2d/options/?vehicleid=383078&intent=buy-used&category=coupe", 
      "make": "MINI", 
      "sub_cat": "John Cooper Works Hatchback 2D", 
      "year": "2013", 
      "model": "Cooper Hardtop", 
      "car_id": "383078"
    }, 
    {
      "category": "Coupes", 
      "url": "/mini/cooper-hardtop/2012-mini-cooper-hardtop/hatchback-2d/options/?vehicleid=382891&intent=buy-used&category=coupe", 
      "make": "MINI", 
      "sub_cat": "Hatchback 2D", 
      "year": "2012", 
      "model": "Cooper Hardtop", 
      "car_id": "382891"
    }, 
    {
      "category": "Coupes", 
      "url": "/mini/cooper-hardtop/2012-mini-cooper-hardtop/s-hatchback-2d/options/?vehicleid=382892&intent=buy-used&category=coupe", 
      "make": "MINI", 
      "sub_cat": "S Hatchback 2D", 
      "year": "2012", 
      "model": "Cooper Hardtop", 
      "car_id": "382892"
    }, 
    {
      "category": "Coupes", 
      "url": "/mini/cooper-hardtop/2012-mini-cooper-hardtop/john-cooper-works-hatchback-2d/options/?vehicleid=382895&intent=buy-used&category=coupe", 
      "make": "MINI", 
      "sub_cat": "John Cooper Works Hatchback 2D", 
      "year": "2012", 
      "model": "Cooper Hardtop", 
      "car_id": "382895"
    }, 
    {
      "category": "Coupes", 
      "url": "/mini/cooper-hardtop/2011-mini-cooper-hardtop/hatchback-2d/options/?vehicleid=382898&intent=buy-used&category=coupe", 
      "make": "MINI", 
      "sub_cat": "Hatchback 2D", 
      "year": "2011", 
      "model": "Cooper Hardtop", 
      "car_id": "382898"
    }, 
    {
      "category": "Coupes", 
      "url": "/mini/cooper-hardtop/2011-mini-cooper-hardtop/s-hatchback-2d/options/?vehicleid=382896&intent=buy-used&category=coupe", 
      "make": "MINI", 
      "sub_cat": "S Hatchback 2D", 
      "year": "2011", 
      "model": "Cooper Hardtop", 
      "car_id": "382896"
    }, 
    {
      "category": "Coupes", 
      "url": "/mini/cooper-hardtop/2011-mini-cooper-hardtop/john-cooper-works-hatchback-2d/options/?vehicleid=382897&intent=buy-used&category=coupe", 
      "make": "MINI", 
      "sub_cat": "John Cooper Works Hatchback 2D", 
      "year": "2011", 
      "model": "Cooper Hardtop", 
      "car_id": "382897"
    }, 
    {
      "category": "Coupes", 
      "url": "/mini/cooper-hardtop/2010-mini-cooper-hardtop/hatchback-2d/options/?vehicleid=382851&intent=buy-used&category=coupe", 
      "make": "MINI", 
      "sub_cat": "Hatchback 2D", 
      "year": "2010", 
      "model": "Cooper Hardtop", 
      "car_id": "382851"
    }, 
    {
      "category": "Coupes", 
      "url": "/mini/cooper-hardtop/2010-mini-cooper-hardtop/s-hatchback-2d/options/?vehicleid=382858&intent=buy-used&category=coupe", 
      "make": "MINI", 
      "sub_cat": "S Hatchback 2D", 
      "year": "2010", 
      "model": "Cooper Hardtop", 
      "car_id": "382858"
    }, 
    {
      "category": "Coupes", 
      "url": "/mini/cooper-hardtop/2010-mini-cooper-hardtop/john-cooper-works-hatchback-2d/options/?vehicleid=382857&intent=buy-used&category=coupe", 
      "make": "MINI", 
      "sub_cat": "John Cooper Works Hatchback 2D", 
      "year": "2010", 
      "model": "Cooper Hardtop", 
      "car_id": "382857"
    }, 
    {
      "category": "Coupes", 
      "url": "/mini/cooper-hardtop/2009-mini-cooper-hardtop/hatchback-2d/options/?vehicleid=382854&intent=buy-used&category=coupe", 
      "make": "MINI", 
      "sub_cat": "Hatchback 2D", 
      "year": "2009", 
      "model": "Cooper Hardtop", 
      "car_id": "382854"
    }, 
    {
      "category": "Coupes", 
      "url": "/mini/cooper-hardtop/2009-mini-cooper-hardtop/s-hatchback-2d/options/?vehicleid=382855&intent=buy-used&category=coupe", 
      "make": "MINI", 
      "sub_cat": "S Hatchback 2D", 
      "year": "2009", 
      "model": "Cooper Hardtop", 
      "car_id": "382855"
    }, 
    {
      "category": "Coupes", 
      "url": "/mini/cooper-hardtop/2009-mini-cooper-hardtop/john-cooper-works-hatchback-2d/options/?vehicleid=382864&intent=buy-used&category=coupe", 
      "make": "MINI", 
      "sub_cat": "John Cooper Works Hatchback 2D", 
      "year": "2009", 
      "model": "Cooper Hardtop", 
      "car_id": "382864"
    }, 
    {
      "category": "Crossovers", 
      "url": "http://www.kbb.com/mini/cooper-countryman/2014-mini-cooper-countryman/hatchback-4d/options/?vehicleid=392936&intent=buy-used&category=crossover", 
      "make": "MINI", 
      "sub_cat": "hatchback-4d", 
      "year": "2014", 
      "model": "Cooper Countryman", 
      "car_id": "392936"
    }, 
    {
      "category": "Crossovers", 
      "url": "/mini/cooper-countryman/2013-mini-cooper-countryman/hatchback-4d/options/?vehicleid=384617&intent=buy-used&category=crossover", 
      "make": "MINI", 
      "sub_cat": "Hatchback 4D", 
      "year": "2013", 
      "model": "Cooper Countryman", 
      "car_id": "384617"
    }, 
    {
      "category": "Crossovers", 
      "url": "/mini/cooper-countryman/2013-mini-cooper-countryman/s-hatchback-4d/options/?vehicleid=384618&intent=buy-used&category=crossover", 
      "make": "MINI", 
      "sub_cat": "S Hatchback 4D", 
      "year": "2013", 
      "model": "Cooper Countryman", 
      "car_id": "384618"
    }, 
    {
      "category": "Crossovers", 
      "url": "/mini/cooper-countryman/2013-mini-cooper-countryman/s-all4-hatchback-4d/options/?vehicleid=384620&intent=buy-used&category=crossover", 
      "make": "MINI", 
      "sub_cat": "S ALL4 Hatchback 4D", 
      "year": "2013", 
      "model": "Cooper Countryman", 
      "car_id": "384620"
    }, 
    {
      "category": "Crossovers", 
      "url": "/mini/cooper-countryman/2013-mini-cooper-countryman/john-cooper-works-all4-hatchback-4d/options/?vehicleid=384619&intent=buy-used&category=crossover", 
      "make": "MINI", 
      "sub_cat": "John Cooper Works ALL4 Hatchback 4D", 
      "year": "2013", 
      "model": "Cooper Countryman", 
      "car_id": "384619"
    }, 
    {
      "category": "Crossovers", 
      "url": "/mini/cooper-countryman/2012-mini-cooper-countryman/hatchback-4d/options/?vehicleid=373526&intent=buy-used&category=crossover", 
      "make": "MINI", 
      "sub_cat": "Hatchback 4D", 
      "year": "2012", 
      "model": "Cooper Countryman", 
      "car_id": "373526"
    }, 
    {
      "category": "Crossovers", 
      "url": "/mini/cooper-countryman/2012-mini-cooper-countryman/s-hatchback-4d/options/?vehicleid=373527&intent=buy-used&category=crossover", 
      "make": "MINI", 
      "sub_cat": "S Hatchback 4D", 
      "year": "2012", 
      "model": "Cooper Countryman", 
      "car_id": "373527"
    }, 
    {
      "category": "Crossovers", 
      "url": "/mini/cooper-countryman/2012-mini-cooper-countryman/s-all4-hatchback-4d/options/?vehicleid=373528&intent=buy-used&category=crossover", 
      "make": "MINI", 
      "sub_cat": "S ALL4 Hatchback 4D", 
      "year": "2012", 
      "model": "Cooper Countryman", 
      "car_id": "373528"
    }, 
    {
      "category": "Crossovers", 
      "url": "/mini/cooper-countryman/2011-mini-cooper-countryman/hatchback-4d/options/?vehicleid=360281&intent=buy-used&category=crossover", 
      "make": "MINI", 
      "sub_cat": "Hatchback 4D", 
      "year": "2011", 
      "model": "Cooper Countryman", 
      "car_id": "360281"
    }, 
    {
      "category": "Crossovers", 
      "url": "/mini/cooper-countryman/2011-mini-cooper-countryman/s-hatchback-4d/options/?vehicleid=360283&intent=buy-used&category=crossover", 
      "make": "MINI", 
      "sub_cat": "S Hatchback 4D", 
      "year": "2011", 
      "model": "Cooper Countryman", 
      "car_id": "360283"
    }, 
    {
      "category": "Crossovers", 
      "url": "/mini/cooper-countryman/2011-mini-cooper-countryman/s-all4-hatchback-4d/options/?vehicleid=360279&intent=buy-used&category=crossover", 
      "make": "MINI", 
      "sub_cat": "S ALL4 Hatchback 4D", 
      "year": "2011", 
      "model": "Cooper Countryman", 
      "car_id": "360279"
    }, 
    {
      "category": "Crossovers", 
      "url": "/mini/cooper-paceman/2014-mini-cooper-paceman/hatchback-2d/options/?vehicleid=392843&intent=buy-used&category=crossover", 
      "make": "MINI", 
      "sub_cat": "Hatchback 2D", 
      "year": "2014", 
      "model": "Cooper Paceman", 
      "car_id": "392843"
    }, 
    {
      "category": "Crossovers", 
      "url": "/mini/cooper-paceman/2014-mini-cooper-paceman/s-hatchback-2d/options/?vehicleid=392844&intent=buy-used&category=crossover", 
      "make": "MINI", 
      "sub_cat": "S Hatchback 2D", 
      "year": "2014", 
      "model": "Cooper Paceman", 
      "car_id": "392844"
    }, 
    {
      "category": "Crossovers", 
      "url": "/mini/cooper-paceman/2013-mini-cooper-paceman/hatchback-2d/options/?vehicleid=384926&intent=buy-used&category=crossover", 
      "make": "MINI", 
      "sub_cat": "Hatchback 2D", 
      "year": "2013", 
      "model": "Cooper Paceman", 
      "car_id": "384926"
    }, 
    {
      "category": "Crossovers", 
      "url": "/mini/cooper-paceman/2013-mini-cooper-paceman/s-hatchback-2d/options/?vehicleid=384927&intent=buy-used&category=crossover", 
      "make": "MINI", 
      "sub_cat": "S Hatchback 2D", 
      "year": "2013", 
      "model": "Cooper Paceman", 
      "car_id": "384927"
    }, 
    {
      "category": "Crossovers", 
      "url": "/mini/cooper-paceman/2013-mini-cooper-paceman/s-all4-hatchback-2d/options/?vehicleid=384928&intent=buy-used&category=crossover", 
      "make": "MINI", 
      "sub_cat": "S ALL4 Hatchback 2D", 
      "year": "2013", 
      "model": "Cooper Paceman", 
      "car_id": "384928"
    }, 
    {
      "category": "Crossovers", 
      "url": "/mini/cooper-paceman/2013-mini-cooper-paceman/john-cooper-works-all4-hatchback-2d/options/?vehicleid=384930&intent=buy-used&category=crossover", 
      "make": "MINI", 
      "sub_cat": "John Cooper Works ALL4 Hatchback 2D", 
      "year": "2013", 
      "model": "Cooper Paceman", 
      "car_id": "384930"
    }, 
    {
      "category": "Hatchbacks", 
      "url": "/mini/cooper/2008-mini-cooper/hatchback-2d/options/?vehicleid=197433&intent=buy-used&category=hatchback", 
      "make": "MINI", 
      "sub_cat": "Hatchback 2D", 
      "year": "2008", 
      "model": "Cooper", 
      "car_id": "197433"
    }, 
    {
      "category": "Hatchbacks", 
      "url": "/mini/cooper/2008-mini-cooper/s-hatchback-2d/options/?vehicleid=197429&intent=buy-used&category=hatchback", 
      "make": "MINI", 
      "sub_cat": "S Hatchback 2D", 
      "year": "2008", 
      "model": "Cooper", 
      "car_id": "197429"
    }, 
    {
      "category": "Hatchbacks", 
      "url": "/mini/cooper/2007-mini-cooper/hatchback-2d/options/?vehicleid=83995&intent=buy-used&category=hatchback", 
      "make": "MINI", 
      "sub_cat": "Hatchback 2D", 
      "year": "2007", 
      "model": "Cooper", 
      "car_id": "83995"
    }, 
    {
      "category": "Hatchbacks", 
      "url": "/mini/cooper/2007-mini-cooper/s-hatchback-2d/options/?vehicleid=83993&intent=buy-used&category=hatchback", 
      "make": "MINI", 
      "sub_cat": "S Hatchback 2D", 
      "year": "2007", 
      "model": "Cooper", 
      "car_id": "83993"
    }, 
    {
      "category": "Hatchbacks", 
      "url": "/mini/cooper/2006-mini-cooper/hatchback-2d/options/?vehicleid=994&intent=buy-used&category=hatchback", 
      "make": "MINI", 
      "sub_cat": "Hatchback 2D", 
      "year": "2006", 
      "model": "Cooper", 
      "car_id": "994"
    }, 
    {
      "category": "Hatchbacks", 
      "url": "/mini/cooper/2006-mini-cooper/s-hatchback-2d/options/?vehicleid=997&intent=buy-used&category=hatchback", 
      "make": "MINI", 
      "sub_cat": "S Hatchback 2D", 
      "year": "2006", 
      "model": "Cooper", 
      "car_id": "997"
    }, 
    {
      "category": "Hatchbacks", 
      "url": "/mini/cooper/2006-mini-cooper/s-gp-hatchback-2d/options/?vehicleid=43512&intent=buy-used&category=hatchback", 
      "make": "MINI", 
      "sub_cat": "S GP Hatchback 2D", 
      "year": "2006", 
      "model": "Cooper", 
      "car_id": "43512"
    }, 
    {
      "category": "Hatchbacks", 
      "url": "/mini/cooper/2005-mini-cooper/hatchback-2d/options/?vehicleid=1119&intent=buy-used&category=hatchback", 
      "make": "MINI", 
      "sub_cat": "Hatchback 2D", 
      "year": "2005", 
      "model": "Cooper", 
      "car_id": "1119"
    }, 
    {
      "category": "Hatchbacks", 
      "url": "/mini/cooper/2005-mini-cooper/s-hatchback-2d/options/?vehicleid=1116&intent=buy-used&category=hatchback", 
      "make": "MINI", 
      "sub_cat": "S Hatchback 2D", 
      "year": "2005", 
      "model": "Cooper", 
      "car_id": "1116"
    }, 
    {
      "category": "Hatchbacks", 
      "url": "/mini/cooper/2004-mini-cooper/hatchback-2d/options/?vehicleid=2929&intent=buy-used&category=hatchback", 
      "make": "MINI", 
      "sub_cat": "Hatchback 2D", 
      "year": "2004", 
      "model": "Cooper", 
      "car_id": "2929"
    }, 
    {
      "category": "Hatchbacks", 
      "url": "/mini/cooper/2004-mini-cooper/s-hatchback-2d/options/?vehicleid=2937&intent=buy-used&category=hatchback", 
      "make": "MINI", 
      "sub_cat": "S Hatchback 2D", 
      "year": "2004", 
      "model": "Cooper", 
      "car_id": "2937"
    }, 
    {
      "category": "Hatchbacks", 
      "url": "/mini/cooper/2003-mini-cooper/hatchback-2d/options/?vehicleid=2689&intent=buy-used&category=hatchback", 
      "make": "MINI", 
      "sub_cat": "Hatchback 2D", 
      "year": "2003", 
      "model": "Cooper", 
      "car_id": "2689"
    }, 
    {
      "category": "Hatchbacks", 
      "url": "/mini/cooper/2003-mini-cooper/s-hatchback-2d/options/?vehicleid=2693&intent=buy-used&category=hatchback", 
      "make": "MINI", 
      "sub_cat": "S Hatchback 2D", 
      "year": "2003", 
      "model": "Cooper", 
      "car_id": "2693"
    }, 
    {
      "category": "Hatchbacks", 
      "url": "/mini/cooper/2002-mini-cooper/hatchback-2d/options/?vehicleid=4340&intent=buy-used&category=hatchback", 
      "make": "MINI", 
      "sub_cat": "Hatchback 2D", 
      "year": "2002", 
      "model": "Cooper", 
      "car_id": "4340"
    }, 
    {
      "category": "Hatchbacks", 
      "url": "/mini/cooper/2002-mini-cooper/s-hatchback-2d/options/?vehicleid=4345&intent=buy-used&category=hatchback", 
      "make": "MINI", 
      "sub_cat": "S Hatchback 2D", 
      "year": "2002", 
      "model": "Cooper", 
      "car_id": "4345"
    }, 
    {
      "category": "Hatchbacks", 
      "url": "/mini/cooper-clubman/2014-mini-cooper-clubman/hatchback-2d/options/?vehicleid=393429&intent=buy-used&category=hatchback", 
      "make": "MINI", 
      "sub_cat": "Hatchback 2D", 
      "year": "2014", 
      "model": "Cooper Clubman", 
      "car_id": "393429"
    }, 
    {
      "category": "Hatchbacks", 
      "url": "/mini/cooper-clubman/2014-mini-cooper-clubman/s-hatchback-2d/options/?vehicleid=393438&intent=buy-used&category=hatchback", 
      "make": "MINI", 
      "sub_cat": "S Hatchback 2D", 
      "year": "2014", 
      "model": "Cooper Clubman", 
      "car_id": "393438"
    }, 
    {
      "category": "Hatchbacks", 
      "url": "/mini/cooper-clubman/2013-mini-cooper-clubman/hatchback-2d/options/?vehicleid=383064&intent=buy-used&category=hatchback", 
      "make": "MINI", 
      "sub_cat": "Hatchback 2D", 
      "year": "2013", 
      "model": "Cooper Clubman", 
      "car_id": "383064"
    }, 
    {
      "category": "Hatchbacks", 
      "url": "/mini/cooper-clubman/2013-mini-cooper-clubman/s-hatchback-2d/options/?vehicleid=383063&intent=buy-used&category=hatchback", 
      "make": "MINI", 
      "sub_cat": "S Hatchback 2D", 
      "year": "2013", 
      "model": "Cooper Clubman", 
      "car_id": "383063"
    }, 
    {
      "category": "Hatchbacks", 
      "url": "/mini/cooper-clubman/2013-mini-cooper-clubman/john-cooper-works-hatchback-2d/options/?vehicleid=383065&intent=buy-used&category=hatchback", 
      "make": "MINI", 
      "sub_cat": "John Cooper Works Hatchback 2D", 
      "year": "2013", 
      "model": "Cooper Clubman", 
      "car_id": "383065"
    }, 
    {
      "category": "Hatchbacks", 
      "url": "/mini/cooper-clubman/2012-mini-cooper-clubman/hatchback-2d/options/?vehicleid=373334&intent=buy-used&category=hatchback", 
      "make": "MINI", 
      "sub_cat": "Hatchback 2D", 
      "year": "2012", 
      "model": "Cooper Clubman", 
      "car_id": "373334"
    }, 
    {
      "category": "Hatchbacks", 
      "url": "/mini/cooper-clubman/2012-mini-cooper-clubman/s-hatchback-2d/options/?vehicleid=373330&intent=buy-used&category=hatchback", 
      "make": "MINI", 
      "sub_cat": "S Hatchback 2D", 
      "year": "2012", 
      "model": "Cooper Clubman", 
      "car_id": "373330"
    }, 
    {
      "category": "Hatchbacks", 
      "url": "/mini/cooper-clubman/2012-mini-cooper-clubman/john-cooper-works-hatchback-2d/options/?vehicleid=373329&intent=buy-used&category=hatchback", 
      "make": "MINI", 
      "sub_cat": "John Cooper Works Hatchback 2D", 
      "year": "2012", 
      "model": "Cooper Clubman", 
      "car_id": "373329"
    }, 
    {
      "category": "Hatchbacks", 
      "url": "/mini/cooper-clubman/2011-mini-cooper-clubman/hatchback-2d/options/?vehicleid=358422&intent=buy-used&category=hatchback", 
      "make": "MINI", 
      "sub_cat": "Hatchback 2D", 
      "year": "2011", 
      "model": "Cooper Clubman", 
      "car_id": "358422"
    }, 
    {
      "category": "Hatchbacks", 
      "url": "/mini/cooper-clubman/2011-mini-cooper-clubman/s-hatchback-2d/options/?vehicleid=358420&intent=buy-used&category=hatchback", 
      "make": "MINI", 
      "sub_cat": "S Hatchback 2D", 
      "year": "2011", 
      "model": "Cooper Clubman", 
      "car_id": "358420"
    }, 
    {
      "category": "Hatchbacks", 
      "url": "/mini/cooper-clubman/2011-mini-cooper-clubman/john-cooper-works-hatchback-2d/options/?vehicleid=358421&intent=buy-used&category=hatchback", 
      "make": "MINI", 
      "sub_cat": "John Cooper Works Hatchback 2D", 
      "year": "2011", 
      "model": "Cooper Clubman", 
      "car_id": "358421"
    }, 
    {
      "category": "Hatchbacks", 
      "url": "/mini/cooper-clubman/2010-mini-cooper-clubman/hatchback-2d/options/?vehicleid=358338&intent=buy-used&category=hatchback", 
      "make": "MINI", 
      "sub_cat": "Hatchback 2D", 
      "year": "2010", 
      "model": "Cooper Clubman", 
      "car_id": "358338"
    }, 
    {
      "category": "Hatchbacks", 
      "url": "/mini/cooper-clubman/2010-mini-cooper-clubman/s-hatchback-2d/options/?vehicleid=358322&intent=buy-used&category=hatchback", 
      "make": "MINI", 
      "sub_cat": "S Hatchback 2D", 
      "year": "2010", 
      "model": "Cooper Clubman", 
      "car_id": "358322"
    }, 
    {
      "category": "Hatchbacks", 
      "url": "/mini/cooper-clubman/2010-mini-cooper-clubman/john-cooper-works-hatchback-2d/options/?vehicleid=358321&intent=buy-used&category=hatchback", 
      "make": "MINI", 
      "sub_cat": "John Cooper Works Hatchback 2D", 
      "year": "2010", 
      "model": "Cooper Clubman", 
      "car_id": "358321"
    }, 
    {
      "category": "Hatchbacks", 
      "url": "/mini/cooper-clubman/2009-mini-cooper-clubman/hatchback-2d/options/?vehicleid=358351&intent=buy-used&category=hatchback", 
      "make": "MINI", 
      "sub_cat": "Hatchback 2D", 
      "year": "2009", 
      "model": "Cooper Clubman", 
      "car_id": "358351"
    }, 
    {
      "category": "Hatchbacks", 
      "url": "/mini/cooper-clubman/2009-mini-cooper-clubman/s-hatchback-2d/options/?vehicleid=358336&intent=buy-used&category=hatchback", 
      "make": "MINI", 
      "sub_cat": "S Hatchback 2D", 
      "year": "2009", 
      "model": "Cooper Clubman", 
      "car_id": "358336"
    }, 
    {
      "category": "Hatchbacks", 
      "url": "/mini/cooper-clubman/2009-mini-cooper-clubman/john-cooper-works-hatchback-2d/options/?vehicleid=358335&intent=buy-used&category=hatchback", 
      "make": "MINI", 
      "sub_cat": "John Cooper Works Hatchback 2D", 
      "year": "2009", 
      "model": "Cooper Clubman", 
      "car_id": "358335"
    }, 
    {
      "category": "Hatchbacks", 
      "url": "/mini/cooper-clubman/2008-mini-cooper-clubman/hatchback-2d/options/?vehicleid=358349&intent=buy-used&category=hatchback", 
      "make": "MINI", 
      "sub_cat": "Hatchback 2D", 
      "year": "2008", 
      "model": "Cooper Clubman", 
      "car_id": "358349"
    }, 
    {
      "category": "Hatchbacks", 
      "url": "/mini/cooper-clubman/2008-mini-cooper-clubman/s-hatchback-2d/options/?vehicleid=358350&intent=buy-used&category=hatchback", 
      "make": "MINI", 
      "sub_cat": "S Hatchback 2D", 
      "year": "2008", 
      "model": "Cooper Clubman", 
      "car_id": "358350"
    }, 
    {
      "category": "Hatchbacks", 
      "url": "http://www.kbb.com/mini/cooper-countryman/2014-mini-cooper-countryman/hatchback-4d/options/?vehicleid=392936&intent=buy-used&category=hatchback", 
      "make": "MINI", 
      "sub_cat": "hatchback-4d", 
      "year": "2014", 
      "model": "Cooper Countryman", 
      "car_id": "392936"
    }, 
    {
      "category": "Hatchbacks", 
      "url": "/mini/cooper-countryman/2013-mini-cooper-countryman/hatchback-4d/options/?vehicleid=384617&intent=buy-used&category=hatchback", 
      "make": "MINI", 
      "sub_cat": "Hatchback 4D", 
      "year": "2013", 
      "model": "Cooper Countryman", 
      "car_id": "384617"
    }, 
    {
      "category": "Hatchbacks", 
      "url": "/mini/cooper-countryman/2013-mini-cooper-countryman/s-hatchback-4d/options/?vehicleid=384618&intent=buy-used&category=hatchback", 
      "make": "MINI", 
      "sub_cat": "S Hatchback 4D", 
      "year": "2013", 
      "model": "Cooper Countryman", 
      "car_id": "384618"
    }, 
    {
      "category": "Hatchbacks", 
      "url": "/mini/cooper-countryman/2013-mini-cooper-countryman/s-all4-hatchback-4d/options/?vehicleid=384620&intent=buy-used&category=hatchback", 
      "make": "MINI", 
      "sub_cat": "S ALL4 Hatchback 4D", 
      "year": "2013", 
      "model": "Cooper Countryman", 
      "car_id": "384620"
    }, 
    {
      "category": "Hatchbacks", 
      "url": "/mini/cooper-countryman/2013-mini-cooper-countryman/john-cooper-works-all4-hatchback-4d/options/?vehicleid=384619&intent=buy-used&category=hatchback", 
      "make": "MINI", 
      "sub_cat": "John Cooper Works ALL4 Hatchback 4D", 
      "year": "2013", 
      "model": "Cooper Countryman", 
      "car_id": "384619"
    }, 
    {
      "category": "Hatchbacks", 
      "url": "/mini/cooper-countryman/2012-mini-cooper-countryman/hatchback-4d/options/?vehicleid=373526&intent=buy-used&category=hatchback", 
      "make": "MINI", 
      "sub_cat": "Hatchback 4D", 
      "year": "2012", 
      "model": "Cooper Countryman", 
      "car_id": "373526"
    }, 
    {
      "category": "Hatchbacks", 
      "url": "/mini/cooper-countryman/2012-mini-cooper-countryman/s-hatchback-4d/options/?vehicleid=373527&intent=buy-used&category=hatchback", 
      "make": "MINI", 
      "sub_cat": "S Hatchback 4D", 
      "year": "2012", 
      "model": "Cooper Countryman", 
      "car_id": "373527"
    }, 
    {
      "category": "Hatchbacks", 
      "url": "/mini/cooper-countryman/2012-mini-cooper-countryman/s-all4-hatchback-4d/options/?vehicleid=373528&intent=buy-used&category=hatchback", 
      "make": "MINI", 
      "sub_cat": "S ALL4 Hatchback 4D", 
      "year": "2012", 
      "model": "Cooper Countryman", 
      "car_id": "373528"
    }, 
    {
      "category": "Hatchbacks", 
      "url": "/mini/cooper-countryman/2011-mini-cooper-countryman/hatchback-4d/options/?vehicleid=360281&intent=buy-used&category=hatchback", 
      "make": "MINI", 
      "sub_cat": "Hatchback 4D", 
      "year": "2011", 
      "model": "Cooper Countryman", 
      "car_id": "360281"
    }, 
    {
      "category": "Hatchbacks", 
      "url": "/mini/cooper-countryman/2011-mini-cooper-countryman/s-hatchback-4d/options/?vehicleid=360283&intent=buy-used&category=hatchback", 
      "make": "MINI", 
      "sub_cat": "S Hatchback 4D", 
      "year": "2011", 
      "model": "Cooper Countryman", 
      "car_id": "360283"
    }, 
    {
      "category": "Hatchbacks", 
      "url": "/mini/cooper-countryman/2011-mini-cooper-countryman/s-all4-hatchback-4d/options/?vehicleid=360279&intent=buy-used&category=hatchback", 
      "make": "MINI", 
      "sub_cat": "S ALL4 Hatchback 4D", 
      "year": "2011", 
      "model": "Cooper Countryman", 
      "car_id": "360279"
    }, 
    {
      "category": "Hatchbacks", 
      "url": "/mini/cooper-coupe/2013-mini-cooper-coupe/coupe-2d/options/?vehicleid=383067&intent=buy-used&category=hatchback", 
      "make": "MINI", 
      "sub_cat": "Coupe 2D", 
      "year": "2013", 
      "model": "Cooper Coupe", 
      "car_id": "383067"
    }, 
    {
      "category": "Hatchbacks", 
      "url": "/mini/cooper-coupe/2013-mini-cooper-coupe/s-coupe-2d/options/?vehicleid=383070&intent=buy-used&category=hatchback", 
      "make": "MINI", 
      "sub_cat": "S Coupe 2D", 
      "year": "2013", 
      "model": "Cooper Coupe", 
      "car_id": "383070"
    }, 
    {
      "category": "Hatchbacks", 
      "url": "/mini/cooper-coupe/2013-mini-cooper-coupe/john-cooper-works-coupe-2d/options/?vehicleid=383071&intent=buy-used&category=hatchback", 
      "make": "MINI", 
      "sub_cat": "John Cooper Works Coupe 2D", 
      "year": "2013", 
      "model": "Cooper Coupe", 
      "car_id": "383071"
    }, 
    {
      "category": "Hatchbacks", 
      "url": "/mini/cooper-coupe/2012-mini-cooper-coupe/coupe-2d/options/?vehicleid=372339&intent=buy-used&category=hatchback", 
      "make": "MINI", 
      "sub_cat": "Coupe 2D", 
      "year": "2012", 
      "model": "Cooper Coupe", 
      "car_id": "372339"
    }, 
    {
      "category": "Hatchbacks", 
      "url": "/mini/cooper-coupe/2012-mini-cooper-coupe/s-coupe-2d/options/?vehicleid=372324&intent=buy-used&category=hatchback", 
      "make": "MINI", 
      "sub_cat": "S Coupe 2D", 
      "year": "2012", 
      "model": "Cooper Coupe", 
      "car_id": "372324"
    }, 
    {
      "category": "Hatchbacks", 
      "url": "/mini/cooper-coupe/2012-mini-cooper-coupe/john-cooper-works-coupe-2d/options/?vehicleid=372325&intent=buy-used&category=hatchback", 
      "make": "MINI", 
      "sub_cat": "John Cooper Works Coupe 2D", 
      "year": "2012", 
      "model": "Cooper Coupe", 
      "car_id": "372325"
    }, 
    {
      "category": "Hatchbacks", 
      "url": "/mini/cooper-hardtop/2013-mini-cooper-hardtop/hatchback-2d/options/?vehicleid=383075&intent=buy-used&category=hatchback", 
      "make": "MINI", 
      "sub_cat": "Hatchback 2D", 
      "year": "2013", 
      "model": "Cooper Hardtop", 
      "car_id": "383075"
    }, 
    {
      "category": "Hatchbacks", 
      "url": "/mini/cooper-hardtop/2013-mini-cooper-hardtop/s-hatchback-2d/options/?vehicleid=383072&intent=buy-used&category=hatchback", 
      "make": "MINI", 
      "sub_cat": "S Hatchback 2D", 
      "year": "2013", 
      "model": "Cooper Hardtop", 
      "car_id": "383072"
    }, 
    {
      "category": "Hatchbacks", 
      "url": "/mini/cooper-hardtop/2013-mini-cooper-hardtop/john-cooper-works-hatchback-2d/options/?vehicleid=383078&intent=buy-used&category=hatchback", 
      "make": "MINI", 
      "sub_cat": "John Cooper Works Hatchback 2D", 
      "year": "2013", 
      "model": "Cooper Hardtop", 
      "car_id": "383078"
    }, 
    {
      "category": "Hatchbacks", 
      "url": "/mini/cooper-hardtop/2012-mini-cooper-hardtop/hatchback-2d/options/?vehicleid=382891&intent=buy-used&category=hatchback", 
      "make": "MINI", 
      "sub_cat": "Hatchback 2D", 
      "year": "2012", 
      "model": "Cooper Hardtop", 
      "car_id": "382891"
    }, 
    {
      "category": "Hatchbacks", 
      "url": "/mini/cooper-hardtop/2012-mini-cooper-hardtop/s-hatchback-2d/options/?vehicleid=382892&intent=buy-used&category=hatchback", 
      "make": "MINI", 
      "sub_cat": "S Hatchback 2D", 
      "year": "2012", 
      "model": "Cooper Hardtop", 
      "car_id": "382892"
    }, 
    {
      "category": "Hatchbacks", 
      "url": "/mini/cooper-hardtop/2012-mini-cooper-hardtop/john-cooper-works-hatchback-2d/options/?vehicleid=382895&intent=buy-used&category=hatchback", 
      "make": "MINI", 
      "sub_cat": "John Cooper Works Hatchback 2D", 
      "year": "2012", 
      "model": "Cooper Hardtop", 
      "car_id": "382895"
    }, 
    {
      "category": "Hatchbacks", 
      "url": "/mini/cooper-hardtop/2011-mini-cooper-hardtop/hatchback-2d/options/?vehicleid=382898&intent=buy-used&category=hatchback", 
      "make": "MINI", 
      "sub_cat": "Hatchback 2D", 
      "year": "2011", 
      "model": "Cooper Hardtop", 
      "car_id": "382898"
    }, 
    {
      "category": "Hatchbacks", 
      "url": "/mini/cooper-hardtop/2011-mini-cooper-hardtop/s-hatchback-2d/options/?vehicleid=382896&intent=buy-used&category=hatchback", 
      "make": "MINI", 
      "sub_cat": "S Hatchback 2D", 
      "year": "2011", 
      "model": "Cooper Hardtop", 
      "car_id": "382896"
    }, 
    {
      "category": "Hatchbacks", 
      "url": "/mini/cooper-hardtop/2011-mini-cooper-hardtop/john-cooper-works-hatchback-2d/options/?vehicleid=382897&intent=buy-used&category=hatchback", 
      "make": "MINI", 
      "sub_cat": "John Cooper Works Hatchback 2D", 
      "year": "2011", 
      "model": "Cooper Hardtop", 
      "car_id": "382897"
    }, 
    {
      "category": "Hatchbacks", 
      "url": "/mini/cooper-hardtop/2010-mini-cooper-hardtop/hatchback-2d/options/?vehicleid=382851&intent=buy-used&category=hatchback", 
      "make": "MINI", 
      "sub_cat": "Hatchback 2D", 
      "year": "2010", 
      "model": "Cooper Hardtop", 
      "car_id": "382851"
    }, 
    {
      "category": "Hatchbacks", 
      "url": "/mini/cooper-hardtop/2010-mini-cooper-hardtop/s-hatchback-2d/options/?vehicleid=382858&intent=buy-used&category=hatchback", 
      "make": "MINI", 
      "sub_cat": "S Hatchback 2D", 
      "year": "2010", 
      "model": "Cooper Hardtop", 
      "car_id": "382858"
    }, 
    {
      "category": "Hatchbacks", 
      "url": "/mini/cooper-hardtop/2010-mini-cooper-hardtop/john-cooper-works-hatchback-2d/options/?vehicleid=382857&intent=buy-used&category=hatchback", 
      "make": "MINI", 
      "sub_cat": "John Cooper Works Hatchback 2D", 
      "year": "2010", 
      "model": "Cooper Hardtop", 
      "car_id": "382857"
    }, 
    {
      "category": "Hatchbacks", 
      "url": "/mini/cooper-hardtop/2009-mini-cooper-hardtop/hatchback-2d/options/?vehicleid=382854&intent=buy-used&category=hatchback", 
      "make": "MINI", 
      "sub_cat": "Hatchback 2D", 
      "year": "2009", 
      "model": "Cooper Hardtop", 
      "car_id": "382854"
    }, 
    {
      "category": "Hatchbacks", 
      "url": "/mini/cooper-hardtop/2009-mini-cooper-hardtop/s-hatchback-2d/options/?vehicleid=382855&intent=buy-used&category=hatchback", 
      "make": "MINI", 
      "sub_cat": "S Hatchback 2D", 
      "year": "2009", 
      "model": "Cooper Hardtop", 
      "car_id": "382855"
    }, 
    {
      "category": "Hatchbacks", 
      "url": "/mini/cooper-hardtop/2009-mini-cooper-hardtop/john-cooper-works-hatchback-2d/options/?vehicleid=382864&intent=buy-used&category=hatchback", 
      "make": "MINI", 
      "sub_cat": "John Cooper Works Hatchback 2D", 
      "year": "2009", 
      "model": "Cooper Hardtop", 
      "car_id": "382864"
    }, 
    {
      "category": "Hatchbacks", 
      "url": "/mini/cooper-paceman/2014-mini-cooper-paceman/hatchback-2d/options/?vehicleid=392843&intent=buy-used&category=hatchback", 
      "make": "MINI", 
      "sub_cat": "Hatchback 2D", 
      "year": "2014", 
      "model": "Cooper Paceman", 
      "car_id": "392843"
    }, 
    {
      "category": "Hatchbacks", 
      "url": "/mini/cooper-paceman/2014-mini-cooper-paceman/s-hatchback-2d/options/?vehicleid=392844&intent=buy-used&category=hatchback", 
      "make": "MINI", 
      "sub_cat": "S Hatchback 2D", 
      "year": "2014", 
      "model": "Cooper Paceman", 
      "car_id": "392844"
    }, 
    {
      "category": "Hatchbacks", 
      "url": "/mini/cooper-paceman/2013-mini-cooper-paceman/hatchback-2d/options/?vehicleid=384926&intent=buy-used&category=hatchback", 
      "make": "MINI", 
      "sub_cat": "Hatchback 2D", 
      "year": "2013", 
      "model": "Cooper Paceman", 
      "car_id": "384926"
    }, 
    {
      "category": "Hatchbacks", 
      "url": "/mini/cooper-paceman/2013-mini-cooper-paceman/s-hatchback-2d/options/?vehicleid=384927&intent=buy-used&category=hatchback", 
      "make": "MINI", 
      "sub_cat": "S Hatchback 2D", 
      "year": "2013", 
      "model": "Cooper Paceman", 
      "car_id": "384927"
    }, 
    {
      "category": "Hatchbacks", 
      "url": "/mini/cooper-paceman/2013-mini-cooper-paceman/s-all4-hatchback-2d/options/?vehicleid=384928&intent=buy-used&category=hatchback", 
      "make": "MINI", 
      "sub_cat": "S ALL4 Hatchback 2D", 
      "year": "2013", 
      "model": "Cooper Paceman", 
      "car_id": "384928"
    }, 
    {
      "category": "Hatchbacks", 
      "url": "/mini/cooper-paceman/2013-mini-cooper-paceman/john-cooper-works-all4-hatchback-2d/options/?vehicleid=384930&intent=buy-used&category=hatchback", 
      "make": "MINI", 
      "sub_cat": "John Cooper Works ALL4 Hatchback 2D", 
      "year": "2013", 
      "model": "Cooper Paceman", 
      "car_id": "384930"
    }, 
    {
      "category": "Wagons", 
      "url": "http://www.kbb.com/mini/cooper-countryman/2014-mini-cooper-countryman/hatchback-4d/options/?vehicleid=392936&intent=buy-used&category=wagon", 
      "make": "MINI", 
      "sub_cat": "hatchback-4d", 
      "year": "2014", 
      "model": "Cooper Countryman", 
      "car_id": "392936"
    }, 
    {
      "category": "Wagons", 
      "url": "/mini/cooper-countryman/2013-mini-cooper-countryman/hatchback-4d/options/?vehicleid=384617&intent=buy-used&category=wagon", 
      "make": "MINI", 
      "sub_cat": "Hatchback 4D", 
      "year": "2013", 
      "model": "Cooper Countryman", 
      "car_id": "384617"
    }, 
    {
      "category": "Wagons", 
      "url": "/mini/cooper-countryman/2013-mini-cooper-countryman/s-hatchback-4d/options/?vehicleid=384618&intent=buy-used&category=wagon", 
      "make": "MINI", 
      "sub_cat": "S Hatchback 4D", 
      "year": "2013", 
      "model": "Cooper Countryman", 
      "car_id": "384618"
    }, 
    {
      "category": "Wagons", 
      "url": "/mini/cooper-countryman/2013-mini-cooper-countryman/s-all4-hatchback-4d/options/?vehicleid=384620&intent=buy-used&category=wagon", 
      "make": "MINI", 
      "sub_cat": "S ALL4 Hatchback 4D", 
      "year": "2013", 
      "model": "Cooper Countryman", 
      "car_id": "384620"
    }, 
    {
      "category": "Wagons", 
      "url": "/mini/cooper-countryman/2013-mini-cooper-countryman/john-cooper-works-all4-hatchback-4d/options/?vehicleid=384619&intent=buy-used&category=wagon", 
      "make": "MINI", 
      "sub_cat": "John Cooper Works ALL4 Hatchback 4D", 
      "year": "2013", 
      "model": "Cooper Countryman", 
      "car_id": "384619"
    }, 
    {
      "category": "Wagons", 
      "url": "/mini/cooper-countryman/2012-mini-cooper-countryman/hatchback-4d/options/?vehicleid=373526&intent=buy-used&category=wagon", 
      "make": "MINI", 
      "sub_cat": "Hatchback 4D", 
      "year": "2012", 
      "model": "Cooper Countryman", 
      "car_id": "373526"
    }, 
    {
      "category": "Wagons", 
      "url": "/mini/cooper-countryman/2012-mini-cooper-countryman/s-hatchback-4d/options/?vehicleid=373527&intent=buy-used&category=wagon", 
      "make": "MINI", 
      "sub_cat": "S Hatchback 4D", 
      "year": "2012", 
      "model": "Cooper Countryman", 
      "car_id": "373527"
    }, 
    {
      "category": "Wagons", 
      "url": "/mini/cooper-countryman/2012-mini-cooper-countryman/s-all4-hatchback-4d/options/?vehicleid=373528&intent=buy-used&category=wagon", 
      "make": "MINI", 
      "sub_cat": "S ALL4 Hatchback 4D", 
      "year": "2012", 
      "model": "Cooper Countryman", 
      "car_id": "373528"
    }, 
    {
      "category": "Wagons", 
      "url": "/mini/cooper-countryman/2011-mini-cooper-countryman/hatchback-4d/options/?vehicleid=360281&intent=buy-used&category=wagon", 
      "make": "MINI", 
      "sub_cat": "Hatchback 4D", 
      "year": "2011", 
      "model": "Cooper Countryman", 
      "car_id": "360281"
    }, 
    {
      "category": "Wagons", 
      "url": "/mini/cooper-countryman/2011-mini-cooper-countryman/s-hatchback-4d/options/?vehicleid=360283&intent=buy-used&category=wagon", 
      "make": "MINI", 
      "sub_cat": "S Hatchback 4D", 
      "year": "2011", 
      "model": "Cooper Countryman", 
      "car_id": "360283"
    }, 
    {
      "category": "Wagons", 
      "url": "/mini/cooper-countryman/2011-mini-cooper-countryman/s-all4-hatchback-4d/options/?vehicleid=360279&intent=buy-used&category=wagon", 
      "make": "MINI", 
      "sub_cat": "S ALL4 Hatchback 4D", 
      "year": "2011", 
      "model": "Cooper Countryman", 
      "car_id": "360279"
    }, 
    {
      "category": "Wagons", 
      "url": "/mini/cooper-paceman/2014-mini-cooper-paceman/hatchback-2d/options/?vehicleid=392843&intent=buy-used&category=wagon", 
      "make": "MINI", 
      "sub_cat": "Hatchback 2D", 
      "year": "2014", 
      "model": "Cooper Paceman", 
      "car_id": "392843"
    }, 
    {
      "category": "Wagons", 
      "url": "/mini/cooper-paceman/2014-mini-cooper-paceman/s-hatchback-2d/options/?vehicleid=392844&intent=buy-used&category=wagon", 
      "make": "MINI", 
      "sub_cat": "S Hatchback 2D", 
      "year": "2014", 
      "model": "Cooper Paceman", 
      "car_id": "392844"
    }, 
    {
      "category": "Wagons", 
      "url": "/mini/cooper-paceman/2013-mini-cooper-paceman/hatchback-2d/options/?vehicleid=384926&intent=buy-used&category=wagon", 
      "make": "MINI", 
      "sub_cat": "Hatchback 2D", 
      "year": "2013", 
      "model": "Cooper Paceman", 
      "car_id": "384926"
    }, 
    {
      "category": "Wagons", 
      "url": "/mini/cooper-paceman/2013-mini-cooper-paceman/s-hatchback-2d/options/?vehicleid=384927&intent=buy-used&category=wagon", 
      "make": "MINI", 
      "sub_cat": "S Hatchback 2D", 
      "year": "2013", 
      "model": "Cooper Paceman", 
      "car_id": "384927"
    }, 
    {
      "category": "Wagons", 
      "url": "/mini/cooper-paceman/2013-mini-cooper-paceman/s-all4-hatchback-2d/options/?vehicleid=384928&intent=buy-used&category=wagon", 
      "make": "MINI", 
      "sub_cat": "S ALL4 Hatchback 2D", 
      "year": "2013", 
      "model": "Cooper Paceman", 
      "car_id": "384928"
    }, 
    {
      "category": "Wagons", 
      "url": "/mini/cooper-paceman/2013-mini-cooper-paceman/john-cooper-works-all4-hatchback-2d/options/?vehicleid=384930&intent=buy-used&category=wagon", 
      "make": "MINI", 
      "sub_cat": "John Cooper Works ALL4 Hatchback 2D", 
      "year": "2013", 
      "model": "Cooper Paceman", 
      "car_id": "384930"
    }
  ]
}